ssqueezepy/README.md
ssqueezepy/__init__.py
ssqueezepy/_cwt.py
ssqueezepy/_gmw.py
ssqueezepy/_ssq_cwt.py
ssqueezepy/_ssq_stft.py
ssqueezepy/_stft.py
ssqueezepy/_test_signals.py
ssqueezepy/algos.py
ssqueezepy/configs.ini
ssqueezepy/configs.py
ssqueezepy/experimental.py
ssqueezepy/ridge_extraction.py
ssqueezepy/ssqueezing.py
ssqueezepy/toolkit.py
ssqueezepy/visuals.py
ssqueezepy/wavelets.py
ssqueezepy/utils/__init__.py
ssqueezepy/utils/backend.py
ssqueezepy/utils/common.py
ssqueezepy/utils/cwt_utils.py
ssqueezepy/utils/fft_utils.py
ssqueezepy/utils/gpu_utils.py
ssqueezepy/utils/stft_utils.py
ssqueezepy-0.6.6.dist-info/LICENSE
ssqueezepy-0.6.6.dist-info/METADATA
ssqueezepy-0.6.6.dist-info/NOTICE.txt
ssqueezepy-0.6.6.dist-info/WHEEL
ssqueezepy-0.6.6.dist-info/top_level.txt
ssqueezepy-0.6.6.dist-info/zip-safe
ssqueezepy-0.6.6.dist-info/RECORD
