Metadata-Version: 2.2
Name: ssqueezepy
Version: 0.6.6
Summary: Synchrosqueezing, wavelet transforms, and time-frequency analysis in Python
Home-page: https://github.com/OverLordGoldDragon/ssqueezepy
Author: John Muradeli
Author-email: john.muradeli@gmail.com
License: MIT
Keywords: signal-processing python synchrosqueezing wavelet-transform cwt stft morse-wavelet ridge-extraction time-frequency time-frequency-analysis visualization
Classifier: Programming Language :: Python :: 3.6
Classifier: Programming Language :: Python :: 3.7
Classifier: Programming Language :: Python :: 3.8
Classifier: Programming Language :: Python :: 3.9
Classifier: Operating System :: OS Independent
Classifier: Intended Audience :: Developers
Classifier: Intended Audience :: Information Technology
Classifier: Intended Audience :: Science/Research
Classifier: Topic :: Utilities
Classifier: Topic :: Multimedia :: Sound/Audio :: Analysis
Classifier: Topic :: Scientific/Engineering
Classifier: Topic :: Scientific/Engineering :: Information Analysis
Classifier: Topic :: Scientific/Engineering :: Bio-Informatics
Classifier: Topic :: Scientific/Engineering :: Visualization
Classifier: Topic :: Software Development
Classifier: Topic :: Software Development :: Libraries :: Python Modules
License-File: LICENSE
License-File: NOTICE.txt
Requires-Dist: numpy
Requires-Dist: numba
Requires-Dist: scipy
Dynamic: author
Dynamic: author-email
Dynamic: classifier
Dynamic: description
Dynamic: description-content-type
Dynamic: home-page
Dynamic: keywords
Dynamic: license
Dynamic: requires-dist
Dynamic: summary
